common/Test.py
common/__init__.py
common/nextpcg.py
common/nextpcg_input.py
common/nextpcg_output.py
common/pson_export.py
pypapi/__init__.py
pypapi/__main__.py
pypapi/const.py
pypapi/dispatch.py
pypapi/dson.py
pypapi/dson_const.py
pypapi/dson_create.py
pypapi/dson_dispatch.py
pypapi/dson_field.py
pypapi/dson_generator.py
pypapi/dson_geo.py
pypapi/dson_pool.py
pypapi/dson_test.py
pypapi/field.py
pypapi/field_heightfield.py
pypapi/field_instanced_staticmesh.py
pypapi/field_texture.py
pypapi/geo.py
pypapi/geo_heightfield.py
pypapi/geo_instanced_staticmesh.py
pypapi/geo_texture.py
pypapi/macro.py
pypapi/meta_helper.py
pypapi/plugin_protocol.py
pypapi/pantry/dson_config.yaml
pypapi/pantry/dson_generator.py
nextpcg-0.6.12.dist-info/METADATA
nextpcg-0.6.12.dist-info/WHEEL
nextpcg-0.6.12.dist-info/entry_points.txt
nextpcg-0.6.12.dist-info/top_level.txt
nextpcg-0.6.12.dist-info/zip-safe
nextpcg-0.6.12.dist-info/RECORD
