Metadata-Version: 2.1
Name: nextpcg
Version: 0.6.12
Summary: pypapi module in NextPCG
Home-page: https://nextpcg.notion.site/Wiki-384dc1d9d9f64306bd8774ff1138f618?pvs=4
Author: GenesisGroup
Author-email: cheneyshen@tencent.com
License: MIT
Classifier: Development Status :: 3 - Alpha
Classifier: Intended Audience :: Developers
Classifier: Programming Language :: Python :: 3
Classifier: Topic :: Software Development :: Libraries
Requires-Python: >=3.6
Requires-Dist: numpy
Requires-Dist: pillow
Requires-Dist: requests
Requires-Dist: pyyaml
Requires-Dist: importlib-resources
